pymate/__init__.py
pymate/cstruct.py
pymate/matecom.py
pymate/util.py
pymate/value.py
pymate/matenet/__init__.py
pymate/matenet/flexnetdc.py
pymate/matenet/fx.py
pymate/matenet/matedevice.py
pymate/matenet/matenet.py
pymate/matenet/matenet_pjon.py
pymate/matenet/matenet_ser.py
pymate/matenet/mx.py
pymate/matenet/tester.py
pymate-2.2.dist-info/LICENSE
pymate-2.2.dist-info/METADATA
pymate-2.2.dist-info/WHEEL
pymate-2.2.dist-info/top_level.txt
pymate-2.2.dist-info/RECORD
